pysecracy/__init__.py
pysecracy/secret_string.py
pysecracy-0.0.1.dist-info/METADATA
pysecracy-0.0.1.dist-info/WHEEL
pysecracy-0.0.1.dist-info/licenses/LICENSE
pysecracy-0.0.1.dist-info/RECORD
